intcode/__init__.py
intcode/handlers/__init__.py
intcode/handlers/io/__init__.py
intcode/handlers/io/stack.py
intcode/handlers/io/std.py
intcode/interfaces/__init__.py
intcode/interfaces/base_op.py
intcode/interfaces/io_handler.py
intcode/interpreter/__init__.py
intcode/interpreter/intcodemachine.py
intcode/interpreter/mappings.py
intcode/interpreter/opcode_dispatcher.py
intcode/interpreter/state.py
intcode/ops/__init__.py
intcode/ops/addition.py
intcode/ops/equals.py
intcode/ops/halt.py
intcode/ops/jump_if_false.py
intcode/ops/jump_if_true.py
intcode/ops/less_than.py
intcode/ops/multiplication.py
intcode/ops/print_value.py
intcode/ops/read_input.py
intcode/ops/shift_relative_base.py
intcode-1.0.0.dist-info/LICENSE
intcode-1.0.0.dist-info/WHEEL
intcode-1.0.0.dist-info/METADATA
intcode-1.0.0.dist-info/RECORD
