Metadata-Version: 2.1
Name: intcode
Version: 1.0.0
Summary: Intcode interpreter for Advent of Code 2019
License: MIT
Author: Javier Luna molina
Author-email: javierlunamolina@gmail.com
Requires-Python: >=3.6,<4.0
Classifier: License :: OSI Approved :: MIT License
Classifier: Programming Language :: Python :: 3
Classifier: Programming Language :: Python :: 3.6
Classifier: Programming Language :: Python :: 3.7
Classifier: Programming Language :: Python :: 3.8
